setuseragent/__init__.py
setuseragent/agent.py
setuseragent/django/__init__.py
setuseragent/django/apps.py
setuseragent/hooks.py
setuseragent-0.7.0.dist-info/WHEEL
setuseragent-0.7.0.dist-info/METADATA
setuseragent-0.7.0.dist-info/RECORD
