Metadata-Version: 2.4
Name: setuseragent
Version: 0.7.0
Summary: Monkey patches for setting user-agent header.
Author: Paul Traylor
Author-email: Paul Traylor <kungfudiscomonkey@gmail.com>
License-Expression: MIT
Classifier: Development Status :: 3 - Alpha
Classifier: Programming Language :: Python :: 3.10
Classifier: Programming Language :: Python :: 3.11
Classifier: Programming Language :: Python :: 3.12
Classifier: Programming Language :: Python :: 3.13
Classifier: Programming Language :: Python :: 3.14
Classifier: Programming Language :: Python :: 3.15
Classifier: Topic :: Internet :: WWW/HTTP
Requires-Python: >=3.10
Project-URL: homepage, https://codeberg.org/kfdm/setuseragent
Project-URL: issues, https://codeberg.org/kfdm/setuseragent/issues
